s1290229_learn/__init__.py
s1290229_learn/statistics/__init__.py
s1290229_learn/statistics/frequenciesOfItems.py
s1290229_learn/visualization/__init__.py
s1290229_learn/visualization/heatMapItemsFrequencies.py
s1290229_learn-2023.8.1.dist-info/LICENSE.txt
s1290229_learn-2023.8.1.dist-info/METADATA
s1290229_learn-2023.8.1.dist-info/WHEEL
s1290229_learn-2023.8.1.dist-info/top_level.txt
s1290229_learn-2023.8.1.dist-info/RECORD
